{"0": "accessories", "1": "additionalHelp", "2": "affirm", "3": "apology", "4": "bad_feedback", "5": "bad_words", "6": "beyaz_esya", "7": "bot_challenge", "8": "chitchat", "9": "deny", "10": "desktop_computer", "11": "ev_aletleri", "12": "express_gratitude", "13": "faq", "14": "filter_products", "15": "gaming_console", "16": "good_feedback", "17": "goodbye", "18": "greet", "19": "heating_cooling", "20": "laptop", "21": "noMoreHelp", "22": "outofscope", "23": "phone", "24": "printer", "25": "tablet", "26": "tv"}